{
  "topics": [
    { "title": "Mathe · Quadratische Gleichungen (Solver)", "url": "/apps/math/quadratic-solver/" },
    { "title": "Sprachen", "url": "/pages/language_lab/apps/index.html" },
    { "title": "Apps (Launcher)", "url": "/pages/language_lab/apps/index.html" },
    { "title": "Store", "url": "/pages/store/index.html" },
    { "title": "Auto-Kauf-Assistent", "url": "/pages/language_lab/apps/tools/auto-kauf-assistent/index.html" },
    { "title": "Quadratgleichung", "url": "/pages/language_lab/apps/mathe/quadratgleichung/index.html" },
    { "title": "Talk Levels", "url": "/pages/language_lab/apps/talk_levels/index.html" },
    { "title": "Karten", "url": "/pages/language_lab/apps/karten/index.html" },
    { "title": "Bibliothek & Ressourcen", "url": "/pages/store/index.html?cat=ressourcen" }
  ]
}
